ledu/__init__.py
ledu/blocks/__init__.py
ledu/blocks/advanced.py
ledu/blocks/base.py
ledu/blocks/code.py
ledu/blocks/heading.py
ledu/blocks/list_item.py
ledu/blocks/media.py
ledu/blocks/paragraph.py
ledu/blocks/table.py
ledu/builder/__init__.py
ledu/builder/page_builder.py
ledu/cli.py
ledu/config.py
ledu/notion/__init__.py
ledu/notion/client.py
ledu/notion/upload.py
ledu/parser/__init__.py
ledu/parser/markdown_parser.py
ledu/parser/rich_text.py
ledu/utils/__init__.py
ledu/utils/enums.py
ledu/utils/errors.py
ledu/utils/typing.py
ledu-0.1.3.dist-info/LICENSE
ledu-0.1.3.dist-info/METADATA
ledu-0.1.3.dist-info/WHEEL
ledu-0.1.3.dist-info/RECORD
