Metadata-Version: 2.1
Name: ledu
Version: 0.1.3
Summary: This repository is build for Bi - directional conversion Notion ⇄ Markdown
Author: Suhail
Author-email: suhailece@gmail.com
Requires-Python: >=3.11,<4.0
Classifier: Programming Language :: Python :: 3
Classifier: Programming Language :: Python :: 3.11
Classifier: Programming Language :: Python :: 3.12
Classifier: Programming Language :: Python :: 3.13
Requires-Dist: markdown-it-py (>=3.0,<4.0)
Requires-Dist: notion-client (>=2.2,<3.0)
Requires-Dist: pydantic (>=2.7,<3.0)
Requires-Dist: rich (>=13.7,<14.0)
